bjcpy/__init__.py
bjcpy/all_styles.py
bjcpy/describe_style.py
bjcpy/find_style.py
bjcpy/fits_style.py
bjcpy/is_style.py
bjcpy/style_data.py
bjcpy/what_style.py
bjcpy-0.1.0.dist-info/LICENSE.txt
bjcpy-0.1.0.dist-info/METADATA
bjcpy-0.1.0.dist-info/WHEEL
bjcpy-0.1.0.dist-info/top_level.txt
bjcpy-0.1.0.dist-info/RECORD
