Metadata-Version: 2.1
Name: bjcpy
Version: 0.1.0
Summary: Python functions based on the 2015 Beer Judge Certification Program (BJCP) style guidelines.
Home-page: https://github.com/blackelbow/bjcpy
Author: blackelbow
Author-email: coude.noir@gmail.com
License: MIT
Keywords: BJCP,Beer,Brewing
Platform: UNKNOWN
Classifier: License :: OSI Approved :: MIT License
Classifier: Programming Language :: Python
Classifier: Programming Language :: Python :: 3
Classifier: Programming Language :: Python :: 3.6
Classifier: Programming Language :: Python :: Implementation :: CPython
Classifier: Programming Language :: Python :: Implementation :: PyPy
Requires-Python: >=3.6.4
